serverless_wsgi.py
serverless_wsgi-3.0.5.dist-info/LICENSE
serverless_wsgi-3.0.5.dist-info/METADATA
serverless_wsgi-3.0.5.dist-info/WHEEL
serverless_wsgi-3.0.5.dist-info/top_level.txt
serverless_wsgi-3.0.5.dist-info/RECORD
