Metadata-Version: 2.1
Name: serverless-wsgi
Version: 3.0.5
Summary: Amazon AWS API Gateway WSGI wrapper
Home-page: https://github.com/logandk/serverless-wsgi
Author: Logan Raarup
Author-email: logan@logan.dk
Keywords: wsgi serverless aws lambda api gateway apigw flask django pyramid
Classifier: Development Status :: 5 - Production/Stable
Classifier: Programming Language :: Python :: 3
Classifier: Intended Audience :: Developers
Classifier: License :: OSI Approved :: MIT License
Classifier: Operating System :: OS Independent
Requires-Python: >3.6
License-File: LICENSE
